glycomass/.DS_Store
glycomass/__init__.py
glycomass/clustering.py
glycomass/main.py
glycomass/mass_list.py
glycomass/mass_list.xlsx
glycomass/process_data.py
glycomass/version.py
glycomass/well_replacement.py
glycomass/__pycache__/__init__.cpython-39.pyc
glycomass/__pycache__/clustering.cpython-39.pyc
glycomass/__pycache__/main.cpython-39.pyc
glycomass/__pycache__/mass_list.cpython-39.pyc
glycomass/__pycache__/process_data.cpython-39.pyc
glycomass/__pycache__/version.cpython-39.pyc
glycomass/__pycache__/well_replacement.cpython-39.pyc
glycomass-2022.3.2.dist-info/METADATA
glycomass-2022.3.2.dist-info/WHEEL
glycomass-2022.3.2.dist-info/top_level.txt
glycomass-2022.3.2.dist-info/RECORD
