Metadata-Version: 2.1
Name: glycomass
Version: 2022.3.2
Summary: Sugar analysis
Home-page: 
Download-URL: 
Author: William Finnigan
Author-email: wjafinnigan@gmail.com
License: UNKNOWN
Keywords: sugar
Platform: UNKNOWN
Classifier: Development Status :: 3 - Alpha
Classifier: License :: OSI Approved :: MIT License
Classifier: Programming Language :: Python :: 3
Requires-Dist: pandas
Requires-Dist: numpy
Requires-Dist: scikit-learn
Requires-Dist: openpyxl
